yt_transcript_dl/__init__.py
yt_transcript_dl/transcript.py
yt_transcript_dl-0.1.0.dist-info/LICENSE.md
yt_transcript_dl-0.1.0.dist-info/METADATA
yt_transcript_dl-0.1.0.dist-info/WHEEL
yt_transcript_dl-0.1.0.dist-info/entry_points.txt
yt_transcript_dl-0.1.0.dist-info/RECORD
