Metadata-Version: 2.1
Name: yt-transcript-dl
Version: 0.1.0
Summary: YouTube Transcript Downloader
License: MIT
Author: Raju Ghorai
Author-email: amirajubolchi001@gmail.com
Requires-Python: >=3.9,<4.0
Classifier: License :: OSI Approved :: MIT License
Classifier: Programming Language :: Python :: 3
Classifier: Programming Language :: Python :: 3.9
Classifier: Programming Language :: Python :: 3.10
Classifier: Programming Language :: Python :: 3.11
Requires-Dist: black (>=23.7.0,<24.0.0)
Requires-Dist: click (>=8.1.7,<9.0.0)
Requires-Dist: mypy (>=1.5.1,<2.0.0)
Requires-Dist: pytest (>=7.4.0,<8.0.0)
Requires-Dist: pytest-cov (>=4.1.0,<5.0.0)
Requires-Dist: radon (>=6.0.1,<7.0.0)
Requires-Dist: toml-cli (>=0.5.0,<0.6.0)
Requires-Dist: twine (>=4.0.2,<5.0.0)
Requires-Dist: xenon (>=0.9.1,<0.10.0)
Requires-Dist: youtube-transcript-api (>=0.6.1,<0.7.0)
